aissue/__init__.py
aissue/apps.py
aissue/exceptions.py
aissue/middleware.py
tests/__init__.py
tests/test_middleware.py
tests/urls.py
aissue-1.0.0.dist-info/METADATA
aissue-1.0.0.dist-info/WHEEL
aissue-1.0.0.dist-info/top_level.txt
aissue-1.0.0.dist-info/RECORD
